CHANGES.rst
MANIFEST.in
README.rst
setup.cfg
setup.py
versioneer.py
PyPrototype.egg-info/PKG-INFO
PyPrototype.egg-info/SOURCES.txt
PyPrototype.egg-info/dependency_links.txt
PyPrototype.egg-info/entry_points.txt
PyPrototype.egg-info/top_level.txt
src/PyPrototype/LICENSE
src/PyPrototype/__init__.py
src/PyPrototype/_version.py
src/PyPrototype/main.py
src/PyPrototype/main_gui.py
src/PyPrototype/mock_PyQt4/Qt.py
src/PyPrototype/mock_PyQt4/QtCore.py
src/PyPrototype/mock_PyQt4/QtGui.py
src/PyPrototype/mock_PyQt4/__init__.py
src/PyPrototype/mock_PyQt4/uic.py